nbdev_template/__init__.py
nbdev_template/_nbdev.py
nbdev_template/s3bz.py
s3bz/__init__.py
s3bz/_nbdev.py
s3bz/s3bz.py
s3bz-0.1.27.dist-info/LICENSE
s3bz-0.1.27.dist-info/METADATA
s3bz-0.1.27.dist-info/WHEEL
s3bz-0.1.27.dist-info/entry_points.txt
s3bz-0.1.27.dist-info/top_level.txt
s3bz-0.1.27.dist-info/RECORD
